Metadata-Version: 2.1
Name: tursor
Version: 0.1.1
Summary: cursor ka bhai
Home-page: UNKNOWN
Author: Krishav
License: UNKNOWN
Platform: UNKNOWN
